{
  "schema": {
    "name": "Generic Alarm Email",
    "type": "dataset",
    "m_icon": null,
    "m_tags": [
      "notification",
      "email"
    ],
    "enabled": true,
    "m_email": "support@pixel-networks.com",
    "m_author": "Pixel",
    "m_picture": null,
    "m_version": "3.0.4",
    "m_longname": null,
    "default_ttl": null,
    "description": "Generic alarm email",
    "m_external_id": "a911e94d-685a-4195-a7aa-e672e48bebad",
    "m_manufacturer": "Pixel",
    "editorgroup": "5d963ea1-cdf2-4e66-8f98-bc07d5f3ea07"
  },
  "properties": [
    {
      "mask": null,
      "type": "string",
      "index": 0,
      "regex": null,
      "units": null,
      "hidden": false,
      "property": "ADDRESS",
      "value_set": null,
      "group_name": "Credentials",
      "description": "Email address",
      "value_range": null,
      "default_value": null,
      "group_description": null
    },
    {
      "mask": null,
      "type": "number",
      "index": 0,
      "regex": null,
      "units": null,
      "hidden": false,
      "property": "PORT",
      "value_set": null,
      "group_name": "Credentials",
      "description": "Port",
      "value_range": null,
      "default_value": null,
      "group_description": null
    },
    {
      "mask": null,
      "type": "string",
      "index": 0,
      "regex": null,
      "units": null,
      "hidden": false,
      "property": "SMTP",
      "value_set": null,
      "group_name": "Credentials",
      "description": "SMTP",
      "value_range": null,
      "default_value": null,
      "group_description": null
    },
    {
      "mask": null,
      "type": "string",
      "index": 0,
      "regex": null,
      "units": null,
      "hidden": false,
      "property": "TOKEN",
      "value_set": null,
      "group_name": "Credentials",
      "description": "Token",
      "value_range": null,
      "default_value": null,
      "group_description": null
    },
    {
      "mask": null,
      "type": "string",
      "index": 0,
      "regex": null,
      "units": null,
      "hidden": false,
      "property": "BODY_TEMPLATE",
      "value_set": null,
      "group_name": "Settings",
      "description": "Email body template",
      "value_range": null,
      "default_value": null,
      "group_description": null
    },
    {
      "mask": null,
      "type": "string",
      "index": 0,
      "regex": null,
      "units": null,
      "hidden": false,
      "property": "FROM",
      "value_set": null,
      "group_name": "Settings",
      "description": "From",
      "value_range": null,
      "default_value": null,
      "group_description": null
    },
    {
      "mask": null,
      "type": "string",
      "index": 0,
      "regex": null,
      "units": null,
      "hidden": false,
      "property": "SUBJECT",
      "value_set": null,
      "group_name": "Settings",
      "description": "Subject",
      "value_range": null,
      "default_value": null,
      "group_description": null
    }
  ]
}